LICENSE
comcrawl/__init__.py
comcrawl/core/__init__.py
comcrawl/core/index_client.py
comcrawl/types.py
comcrawl/utils/__init__.py
comcrawl/utils/download.py
comcrawl/utils/initialization.py
comcrawl/utils/multithreading.py
comcrawl/utils/search.py
comcrawl-1.0.2.dist-info/LICENSE
comcrawl-1.0.2.dist-info/WHEEL
comcrawl-1.0.2.dist-info/METADATA
comcrawl-1.0.2.dist-info/RECORD
