Metadata-Version: 2.1
Name: comcrawl
Version: 1.0.2
Summary: A python utility for downloading Common Crawl data.
Home-page: https://github.com/michaelharms/comcrawl
License: MIT
Keywords: commoncrawl,machine-learning,nlp,data,common-crawl,scraping,deep-learning,training-dataset
Author: Michael Harms
Author-email: michaelharms95@icloud.com
Requires-Python: >=3.6,<4.0
Classifier: Intended Audience :: Developers
Classifier: Intended Audience :: Science/Research
Classifier: License :: OSI Approved :: MIT License
Classifier: Programming Language :: Python :: 3
Classifier: Programming Language :: Python :: 3.6
Classifier: Programming Language :: Python :: 3.7
Classifier: Programming Language :: Python :: 3.8
Classifier: Topic :: Scientific/Engineering
Classifier: Topic :: Software Development :: Libraries
Classifier: Topic :: Software Development :: Libraries :: Python Modules
Classifier: Typing :: Typed
Requires-Dist: requests (>=2.22.0,<3.0.0)
Project-URL: Repository, https://github.com/michaelharms/comcrawl
